d3_dpa_chile/__init__.py
d3_dpa_chile/models.py
d3_dpa_chile/management/__init__.py
d3_dpa_chile/management/commands/__init__.py
d3_dpa_chile/management/commands/populate_dpa_chile.py
d3_dpa_chile/migrations/0001_initial.py
d3_dpa_chile/migrations/__init__.py
django3_dpa_chile-0.4.0.dist-info/LICENSE
django3_dpa_chile-0.4.0.dist-info/METADATA
django3_dpa_chile-0.4.0.dist-info/WHEEL
django3_dpa_chile-0.4.0.dist-info/top_level.txt
django3_dpa_chile-0.4.0.dist-info/RECORD
