Metadata-Version: 2.1
Name: django3-dpa-chile
Version: 0.4.0
Summary: Political-Administrative Division of Chile
Home-page: https://github.com/zubus/django3-dpa-chile
Author: Cristian Zúñiga
Author-email: contacto@nyumba.cl
License: MIT
Keywords: django chile regiones comunas provincias
Classifier: Development Status :: 5 - Production/Stable
Classifier: Environment :: Web Environment
Classifier: Framework :: Django
Classifier: Framework :: Django :: 3.2
Classifier: Intended Audience :: Developers
Classifier: License :: OSI Approved :: MIT License
Classifier: Natural Language :: Spanish
Classifier: Operating System :: Unix
Classifier: Programming Language :: Python
Classifier: Programming Language :: Python :: 3
Classifier: Programming Language :: Python :: 3.6
Classifier: Programming Language :: Python :: 3.7
Classifier: Programming Language :: Python :: 3.8
Classifier: Programming Language :: Python :: 3.9
License-File: LICENSE
Requires-Dist: Django (>=3.2)
Requires-Dist: requests
